src/__init__.py
src/mdtorst.py
md_rst-0.1.5.dist-info/LICENSE
md_rst-0.1.5.dist-info/METADATA
md_rst-0.1.5.dist-info/WHEEL
md_rst-0.1.5.dist-info/entry_points.txt
md_rst-0.1.5.dist-info/top_level.txt
md_rst-0.1.5.dist-info/RECORD
