Metadata-Version: 2.1
Name: md-rst
Version: 0.1.5
Summary: CLI converter Marckdown to reStructuredText (.md to .rst)
Home-page: https://github.com/croketillo/md-rst
Author: croketillo
Author-email: croketillo@gmail.com
License: GNU GENERAL PUBLIC LICENSE
Keywords: markdown rst converter cli
Platform: UNKNOWN
Classifier: Environment :: Console
Classifier: Intended Audience :: End Users/Desktop
Classifier: Intended Audience :: Other Audience
Classifier: Intended Audience :: Developers
Classifier: Programming Language :: Python :: 3
Classifier: Programming Language :: Python :: 3.6
Classifier: Programming Language :: Python :: 3.7
Classifier: Programming Language :: Python :: 3.8
Classifier: Topic :: Text Processing :: Markup :: reStructuredText
Classifier: Topic :: Text Processing :: Markup :: Markdown
Classifier: Topic :: Terminals
Classifier: Topic :: Utilities
License-File: LICENSE
Requires-Dist: click
Requires-Dist: pypandoc
